[{"name_Report":"Réalisations du Bureau des Affaires Administratives et Financières","id":1,"numero":"123","region":"Bongolava","cirfin":"","mois":"Janvier","produit":"Taux d’exécution","realisation":"52","valeurCible":"52","pourcentageRealisation":"100"},{"name_Report":"Réalisations du Bureau des Affaires Administratives et Financières","id":2,"numero":"123","region":"Bongolava","cirfin":"","mois":"Janvier","produit":"Nombre de dossiers envoyés au SPERS","realisation":"52","valeurCible":"52","pourcentageRealisation":"100"},{"name_Report":"Réalisations du Bureau des Affaires Administratives et Financières","id":3,"numero":"123","region":"Bongolava","cirfin":"","mois":"Janvier","produit":"Nombre de dossiers de personnel traités localement","realisation":"32","valeurCible":"52","pourcentageRealisation":"62"},{"name_Report":"Réalisations de la Division Chargée des Finances Locales et Tutelle des EPN","id":4,"numero":"123","region":"Bongolava","cirfin":"","mois":"Janvier","produit":"Budgets primitifs visés","realisation":"52","valeurCible":"52","pourcentageRealisation":"100"},{"name_Report":"Réalisations de la Division Chargée des Finances Locales et Tutelle des EPN","id":5,"numero":"123","region":"Bongolava","cirfin":"","mois":"Janvier","produit":"Budgets rectificatifs visés","realisation":"52","valeurCible":"52","pourcentageRealisation":"100"},{"name_Report":"Réalisations de la Division Chargée des Finances Locales et Tutelle des EPN","id":6,"numero":"123","region":"Bongolava","cirfin":"","mois":"Janvier","produit":"Budgets additionnels visés","realisation":"52","valeurCible":"52","pourcentageRealisation":"100"},{"name_Report":"Réalisations de la Division Chargée des Finances Locales et Tutelle des EPN","id":7,"numero":"123","region":"Bongolava","cirfin":"","mois":"Janvier","produit":"Comptes administratifs visés","realisation":"52","valeurCible":"52","pourcentageRealisation":"100"},{"name_Report":"Réalisations de la Division Chargée des Finances Locales et Tutelle des EPN","id":8,"numero":"123","region":"Bongolava","cirfin":"","mois":"Janvier","produit":"Dossiers de personnel EPN Visés : renouvellement, recrutement, retraite…","realisation":"52","valeurCible":"52","pourcentageRealisation":"100"},{"name_Report":"Réalisations de la Division Chargée des Finances Locales et Tutelle des EPN","id":9,"numero":"123","region":"Bongolava","cirfin":"","mois":"Janvier","produit":"CTD formées en Budget de Programmes","realisation":"52","valeurCible":"52","pourcentageRealisation":"100"},{"name_Report":"Réalisations de la Division Chargée des Finances Locales et Tutelle des EPN","id":10,"numero":"123","region":"Bongolava","cirfin":"","mois":"Janvier","produit":"Responsables appuyés et assistés sur l’élaboration de Budget primitif","realisation":"52","valeurCible":"52","pourcentageRealisation":"100"},{"name_Report":"Réalisations de la Division Chargée des Finances Locales et Tutelle des EPN","id":11,"numero":"123","region":"Bongolava","cirfin":"","mois":"Janvier","produit":"Responsables appuyés et assistés sur l’élaboration de compte administratif","realisation":"52","valeurCible":"52","pourcentageRealisation":"100"},null,{"name_Report":"Réalisations du Bureau des Affaires Administratives et Financières","id":13,"numero":"455","region":"Bongolava","cirfin":"Moramanga","mois":"Janvier","produit":"Taux d’exécution","realisation":"78","valeurCible":"76","pourcentageRealisation":"103"},null,{"name_Report":"Réalisations de la Division Exécution Budgétaire et Remboursement des Frais Médicaux","id":15,"numero":"452","region":"Bongolava","cirfin":"Moramanga","mois":"Janvier","produit":"BCSE collectés","realisation":"45","valeurCible":"52","pourcentageRealisation":"87"},{"name_Report":"Réalisations du Centre Informatique Régional","id":16,"numero":"452","region":"Bongolava","cirfin":"Moramanga","mois":"Janvier","produit":"Utilisateurs-assistés:SIGFP,SIGMP,SYGECD","realisation":45,"valeurCible":52,"pourcentageRealisation":"87"}]